[{"s": "280-ballov-v-pyaterochke-eto-skolko", "t": "280 баллов в Пятерочке: сколько это рублей и как потратить", "i": "💰", "c": "bonusy-i-bally"}, {"s": "280-ballov-pyaterochke-eto-skolko-rublej", "t": "280 баллов Пятерочке: сколько это рублей и как потратить", "i": "💰", "c": "bonusy-i-bally"}, {"s": "287-ballov-v-pyaterochke-eto-skolko-rublej", "t": "287 баллов в Пятерочке: сколько это рублей и как потратить", "i": "💰", "c": "bonusy-i-bally"}, {"s": "28-ballov-v-pyaterochke-eto-skolko-rublej", "t": "28 баллов в Пятерочке: стоимость и конвертация в рубли", "i": "💰", "c": "bonusy-i-bally"}, {"s": "288-ballov-v-pyaterochke-eto-skolko-v-rublyakh", "t": "288 баллов в Пятерочке: сколько это рублей и как потратить", "i": "💰", "c": "bonusy-i-bally"}, {"s": "2800-ballov-v-pyaterochke-skolko-v-rublyakh", "t": "2800 баллов в Пятерочке: сколько это в рублях и как потратить", "i": "💰", "c": "bonusy-i-bally"}, {"s": "283-balla-v-pyaterochke-skolko-rublej", "t": "283 балла в Пятерочке: сколько это рублей и как потратить", "i": "💰", "c": "bonusy-i-bally"}]